llm_templates_fabric.py
llm_templates_fabric-0.2.dist-info/licenses/LICENSE
llm_templates_fabric-0.2.dist-info/METADATA
llm_templates_fabric-0.2.dist-info/WHEEL
llm_templates_fabric-0.2.dist-info/entry_points.txt
llm_templates_fabric-0.2.dist-info/top_level.txt
llm_templates_fabric-0.2.dist-info/RECORD
