Metadata-Version: 2.4
Name: llm-templates-fabric
Version: 0.2
Summary: Load LLM templates from Fabric
Author: Simon Willison
License: Apache-2.0
Project-URL: Homepage, https://github.com/simonw/llm-templates-fabric
Project-URL: Changelog, https://github.com/simonw/llm-templates-fabric/releases
Project-URL: Issues, https://github.com/simonw/llm-templates-fabric/issues
Project-URL: CI, https://github.com/simonw/llm-templates-fabric/actions
Classifier: License :: OSI Approved :: Apache Software License
Requires-Python: >=3.9
License-File: LICENSE
Requires-Dist: llm>=0.24
Requires-Dist: httpx
Provides-Extra: test
Requires-Dist: pytest; extra == "test"
Dynamic: license-file
